MANIFEST.in
README.rst
setup.cfg
setup.py
asynciomeasures/__init__.py
asynciomeasures/checks.py
asynciomeasures/collectors.py
asynciomeasures/events.py
asynciomeasures/metrics.py
asynciomeasures/util.py
asynciomeasures.egg-info/PKG-INFO
asynciomeasures.egg-info/SOURCES.txt
asynciomeasures.egg-info/dependency_links.txt
asynciomeasures.egg-info/top_level.txt
asynciomeasures/clients/__init__.py
asynciomeasures/clients/bases.py
asynciomeasures/clients/datadog/__init__.py
asynciomeasures/clients/datadog/client.py
asynciomeasures/clients/datadog/formatting.py
asynciomeasures/clients/statsd/__init__.py
asynciomeasures/clients/statsd/client.py
asynciomeasures/clients/statsd/formatting.py
asynciomeasures/reporters/__init__.py
asynciomeasures/reporters/statsd_reporter.py
tests/__init__.py
tests/conftest.py
tests/test_datadog.py
tests/test_statsd.py